ifcpatch/__init__.py
ifcpatch/__main__.py
ifcpatch/recipes/AssignConstituentFractions.py
ifcpatch/recipes/ConvertLengthUnit.py
ifcpatch/recipes/ConvertNestToAggregate.py
ifcpatch/recipes/ConvertPropertiesToQuantities.py
ifcpatch/recipes/DowngradeIndexedPolyCurve.py
ifcpatch/recipes/ExtractElements.py
ifcpatch/recipes/ExtractPropertiesToSQLite.py
ifcpatch/recipes/FixArchiCADToRevitDoorSwings.py
ifcpatch/recipes/FixArchiCADToRevitSpaces.py
ifcpatch/recipes/FixRevit2025TINs.py
ifcpatch/recipes/FixRevitClassificationCodeTypes.py
ifcpatch/recipes/FixRevitTINs.py
ifcpatch/recipes/Ifc2Sql.py
ifcpatch/recipes/MergeDuplicateTypes.py
ifcpatch/recipes/MergeProjects.py
ifcpatch/recipes/MergeStyles.py
ifcpatch/recipes/Migrate.py
ifcpatch/recipes/OffsetObjectPlacements.py
ifcpatch/recipes/OffsetStoreyElevations.py
ifcpatch/recipes/Optimise.py
ifcpatch/recipes/PurgeData.py
ifcpatch/recipes/RecycleNonRootedElements.py
ifcpatch/recipes/RegenerateGlobalIds.py
ifcpatch/recipes/RemoveRevitUniformatClassification.py
ifcpatch/recipes/RemoveSiteRepresentation.py
ifcpatch/recipes/ResetAbsoluteCoordinates.py
ifcpatch/recipes/ResetSpatialElementLocations.py
ifcpatch/recipes/SetFalseOrigin.py
ifcpatch/recipes/SetRefElevation.py
ifcpatch/recipes/SetWorldCoordinateSystem.py
ifcpatch/recipes/SplitByBuildingStorey.py
ifcpatch/recipes/TessellateElements.py
ifcpatch/recipes/UnsharePsets.py
ifcpatch/recipes/__init__.py
ifcpatch-0.8.3.dist-info/METADATA
ifcpatch-0.8.3.dist-info/WHEEL
ifcpatch-0.8.3.dist-info/top_level.txt
ifcpatch-0.8.3.dist-info/RECORD
