Metadata-Version: 2.4
Name: ifcpatch
Version: 0.8.3
Summary: IFC patching utility
Author-email: Dion Moult <dion@thinkmoult.com>
Project-URL: Homepage, http://ifcopenshell.org
Project-URL: Documentation, https://docs.ifcopenshell.org
Project-URL: Issues, https://github.com/IfcOpenShell/IfcOpenShell/issues
Keywords: IFC,BIM
Classifier: Programming Language :: Python :: 3
Classifier: License :: OSI Approved :: GNU Lesser General Public License v3 or later (LGPLv3+)
Requires-Dist: ifcopenshell
Requires-Dist: toposort
Requires-Dist: numpy
Provides-Extra: advanced
Requires-Dist: sqlite3; extra == "advanced"
Requires-Dist: mysql-connector-python; extra == "advanced"
